Workbook

Sheet README
A1: NileCare – ISO/IEC 27001:2022 Risk Assessment (Practice Project)
A3: Company (fictional) | B3: NileCare – private clinics group in Cairo, 3 branches, ~120 staff, electronic patient records (EMR) and an online booking portal.
A4: Purpose | B4: Portfolio GRC project: asset inventory, risk register, and treatment plan mapped to ISO 27001:2022 Annex A.
A5: Method | B5: Risk = Likelihood (1-5) x Impact (1-5). Impact is driven by the asset's Confidentiality/Integrity/Availability ratings. See 'Scoring Key'.
A7: Sheets
A8: Asset Inventory | B8: 20 assets with owner, location, C/I/A ratings (1-3) and auto-calculated criticality.
A9: Risk Register | B9: 16 risks linked to assets by Asset ID. Inherent and residual scores and levels are formulas.
A10: Scoring Key | B10: Likelihood and impact scales, risk-level thresholds (the thresholds are read by the formulas).
A11: Summary | B11: Auto-counts of risks by level, before and after treatment.
A13: Legend
A14: Blue text | B14: Input cells – edit these (ratings, owners, text).
A15: Black text | B15: Formulas – do not overwrite.
A16: Assumptions | B16: All assets, risks, owners and ratings are fictional and invented for practice. Annex A references follow the 2022 edition numbering. Egyptian Personal Data Protection Law No. 151 of 2020 is referenced for PII-related risks.

Sheet Asset Inventory
A1: Asset ID | B1: Asset Name | C1: Type | D1: Description | E1: Location | F1: Owner | G1: Confidentiality (1-3) | H1: Integrity (1-3) | I1: Availability (1-3) | J1: Criticality (auto)
A2: A-01 | B2: EMR System (patient records) | C2: Application | D2: Electronic medical records used by all clinics | E2: Cloud (Egyptian hosting provider) | F2: Head of Medical Operations | G2: 3 | H2: 3 | I2: 3 | J2: =IF(MAX(G2:I2)=3,"High",IF(MAX(G2:I2)=2,"Medium","Low")) -> High
A3: A-02 | B3: Patient Database | C3: Data | D3: Patient identity, history, diagnoses, prescriptions | E3: Primary DB server | F3: IT Manager | G3: 3 | H3: 3 | I3: 3 | J3: =IF(MAX(G3:I3)=3,"High",IF(MAX(G3:I3)=2,"Medium","Low")) -> High
A4: A-03 | B4: Online Booking Portal | C4: Application | D4: Public website for appointment booking | E4: Cloud web hosting | F4: Digital Services Lead | G4: 2 | H4: 2 | I4: 3 | J4: =IF(MAX(G4:I4)=3,"High",IF(MAX(G4:I4)=2,"Medium","Low")) -> High
A5: A-04 | B5: Core DB Server | C5: Hardware | D5: On-prem server hosting EMR database replica | E5: HQ server room, Cairo | F5: IT Manager | G5: 3 | H5: 3 | I5: 3 | J5: =IF(MAX(G5:I5)=3,"High",IF(MAX(G5:I5)=2,"Medium","Low")) -> High
A6: A-05 | B6: File Server | C6: Hardware | D6: Shared drives for admin and finance documents | E6: HQ server room, Cairo | F6: IT Manager | G6: 2 | H6: 2 | I6: 2 | J6: =IF(MAX(G6:I6)=3,"High",IF(MAX(G6:I6)=2,"Medium","Low")) -> Medium
A7: A-06 | B7: Backup System (NAS + cloud copy) | C7: Hardware | D7: Nightly backups of EMR and file server | E7: HQ server room + cloud | F7: IT Manager | G7: 3 | H7: 3 | I7: 2 | J7: =IF(MAX(G7:I7)=3,"High",IF(MAX(G7:I7)=2,"Medium","Low")) -> High
A8: A-07 | B8: Core Network (firewalls, switches) | C8: Network | D8: Firewalls, core and branch switches | E8: HQ and 3 branches | F8: Network Administrator | G8: 2 | H8: 3 | I8: 3 | J8: =IF(MAX(G8:I8)=3,"High",IF(MAX(G8:I8)=2,"Medium","Low")) -> High
A9: A-08 | B9: Branch VPN Links | C9: Network | D9: Site-to-site VPN between branches and HQ | E9: All branches | F9: Network Administrator | G9: 3 | H9: 3 | I9: 3 | J9: =IF(MAX(G9:I9)=3,"High",IF(MAX(G9:I9)=2,"Medium","Low")) -> High
A10: A-09 | B10: Staff Workstations (~80) | C10: Hardware | D10: Reception and admin PCs | E10: All branches | F10: IT Support Lead | G10: 2 | H10: 2 | I10: 2 | J10: =IF(MAX(G10:I10)=3,"High",IF(MAX(G10:I10)=2,"Medium","Low")) -> Medium
A11: A-10 | B11: Doctor Laptops (~35) | C11: Hardware | D11: Laptops used for consultations and EMR access | E11: Clinics | F11: IT Support Lead | G11: 3 | H11: 3 | I11: 2 | J11: =IF(MAX(G11:I11)=3,"High",IF(MAX(G11:I11)=2,"Medium","Low")) -> High
A12: A-11 | B12: Email and Collaboration (SaaS) | C12: Service | D12: Corporate email and file sharing | E12: Cloud SaaS | F12: IT Manager | G12: 3 | H12: 2 | I12: 2 | J12: =IF(MAX(G12:I12)=3,"High",IF(MAX(G12:I12)=2,"Medium","Low")) -> High
A13: A-12 | B13: Active Directory | C13: Service | D13: Staff identities, groups and authentication | E13: HQ server room | F13: IT Manager | G13: 3 | H13: 3 | I13: 3 | J13: =IF(MAX(G13:I13)=3,"High",IF(MAX(G13:I13)=2,"Medium","Low")) -> High
... A21: A-20 | B21: Third-party IT and EMR Vendor | C21: Supplier | D21: Vendor providing EMR hosting and support | E21: External | F21: Procurement Manager | G21: 3 | H21: 3 | I21: 3 | J21: =IF(MAX(G21:I21)=3,"High",IF(MAX(G21:I21)=2,"Medium","Low")) -> High

Sheet Risk Register
A1: Risk ID | B1: Asset ID | C1: Asset Name (auto) | D1: Threat | E1: Vulnerability | F1: Likelihood (1-5) | G1: Impact (1-5) | H1: Inherent Score | I1: Inherent Level | J1: Existing Controls | K1: ISO 27001:2022 Annex A Control | L1: Treatment | M1: Planned Actions | N1: Risk Owner | O1: Target Date | P1: Residual Likelihood | Q1: Residual Impact | R1: Residual Score | S1: Residual Level | T1: Status
A2: R-01 | B2: A-01 | C2: =IFERROR(INDEX('Asset Inventory'!$B$2:$B$21,MATCH(B2,'Asset Inventory'!$A$2:$A$21,0)),"Unknown asset") -> EMR System (patient records) | D2: Ransomware encrypts EMR and databases | E2: Flat network, delayed patching, limited EDR coverage | F2: 4 | G2: 5 | H2: =F2*G2 -> 20 | I2: =IF(H2>='Scoring Key'!$B$12,"Critical",IF(H2>='Scoring Key'!$B$11,"High",IF(H2>='Scoring Key'!$B$10,"Medium","Low"))) -> Critical | J2: Daily backups; basic antivirus | K2: A.8.7 Protection against malware; A.8.8 Technical vulnerabilities | L2: Mitigate | M2: Deploy EDR on servers and laptops; network segmentation; monthly patch cycle | N2: IT Manager | O2: 2027-03-31 | P2: 2 | Q2: 4 | R2: =P2*Q2 -> 8 | S2: =IF(R2>='Scoring Key'!$B$12,"Critical",IF(R2>='Scoring Key'!$B$11,"High",IF(R2>='Scoring Key'!$B$10,"Medium","Low"))) -> Medium | T2: Planned
A3: R-02 | B3: A-02 | C3: =IFERROR(INDEX('Asset Inventory'!$B$2:$B$21,MATCH(B3,'Asset Inventory'!$A$2:$A$21,0)),"Unknown asset") -> Patient Database | D3: Unauthorized access to patient records by staff (snooping) | E3: No role-based access review; shared accounts at some reception desks | F3: 4 | G3: 4 | H3: =F3*G3 -> 16 | I3: =IF(H3>='Scoring Key'!$B$12,"Critical",IF(H3>='Scoring Key'!$B$11,"High",IF(H3>='Scoring Key'!$B$10,"Medium","Low"))) -> High | J3: Basic AD groups | K3: A.5.15 Access control; A.8.15 Logging | L3: Mitigate | M3: RBAC redesign; disable shared accounts; log and review EMR access | N3: Head of Medical Operations | O3: 2027-02-28 | P3: 2 | Q3: 3 | R3: =P3*Q3 -> 6 | S3: =IF(R3>='Scoring Key'!$B$12,"Critical",IF(R3>='Scoring Key'!$B$11,"High",IF(R3>='Scoring Key'!$B$10,"Medium","Low"))) -> Medium | T3: Planned
A4: R-03 | B4: A-03 | C4: =IFERROR(INDEX('Asset Inventory'!$B$2:$B$21,MATCH(B4,'Asset Inventory'!$A$2:$A$21,0)),"Unknown asset") -> Online Booking Portal | D4: Phishing leads to credential theft | E4: Low security awareness; MFA not enforced on email | F4: 5 | G4: 4 | H4: =F4*G4 -> 20 | I4: =IF(H4>='Scoring Key'!$B$12,"Critical",IF(H4>='Scoring Key'!$B$11,"High",IF(H4>='Scoring Key'!$B$10,"Medium","Low"))) -> Critical | J4: Spam filter | K4: A.6.3 Awareness and training; A.8.5 Secure authentication | L4: Mitigate | M4: Enforce MFA on email and VPN; quarterly phishing simulations | N4: IT Manager | O4: 2027-01-31 | P4: 3 | Q4: 3 | R4: =P4*Q4 -> 9 | S4: =IF(R4>='Scoring Key'!$B$12,"Critical",IF(R4>='Scoring Key'!$B$11,"High",IF(R4>='Scoring Key'!$B$10,"Medium","Low"))) -> Medium | T4: In progress
A5: R-04 | B5: A-06 | C5: =IFERROR(INDEX('Asset Inventory'!$B$2:$B$21,MATCH(B5,'Asset Inventory'!$A$2:$A$21,0)),"Unknown asset") -> Backup System (NAS + cloud copy) | D5: Backups corrupted or unrecoverable during an incident | E5: Restore never tested; backup NAS on same network as production | F5: 3 | G5: 5 | H5: =F5*G5 -> 15 | I5: =IF(H5>='Scoring Key'!$B$12,"Critical",IF(H5>='Scoring Key'!$B$11,"High",IF(H5>='Scoring Key'!$B$10,"Medium","Low"))) -> High | J5: Nightly backups | K5: A.8.13 Information backup; A.5.30 ICT readiness for continuity | L5: Mitigate | M5: Offline/immutable copy; quarterly restore tests | N5: IT Manager | O5: 2027-02-15 | P5: 2 | Q5: 3 | R5: =P5*Q5 -> 6 | S5: =IF(R5>='Scoring Key'!$B$12,"Critical",IF(R5>='Scoring Key'!$B$11,"High",IF(R5>='Scoring Key'!$B$10,"Medium","Low"))) -> Medium | T5: Planned
A6: R-05 | B6: A-03 | C6: =IFERROR(INDEX('Asset Inventory'!$B$2:$B$21,MATCH(B6,'Asset Inventory'!$A$2:$A$21,0)),"Unknown asset") -> Online Booking Portal | D6: Web attack (SQL injection, defacement) on booking portal | E6: No WAF; no regular vulnerability scans | F6: 3 | G6: 3 | H6: =F6*G6 -> 9 | I6: =IF(H6>='Scoring Key'!$B$12,"Critical",IF(H6>='Scoring Key'!$B$11,"High",IF(H6>='Scoring Key'!$B$10,"Medium","Low"))) -> Medium | J6: HTTPS only | K6: A.8.8 Technical vulnerabilities; A.8.28 Secure coding | L6: Mitigate | M6: Deploy WAF; quarterly vulnerability scan and annual pentest | N6: Digital Services Lead | O6: 2027-04-30 | P6: 2 | Q6: 2 | R6: =P6*Q6 -> 4 | S6: =IF(R6>='Scoring Key'!$B$12,"Critical",IF(R6>='Scoring Key'!$B$11,"High",IF(R6>='Scoring Key'!$B$10,"Medium","Low"))) -> Low | T6: Planned
A7: R-06 | B7: A-20 | C7: =IFERROR(INDEX('Asset Inventory'!$B$2:$B$21,MATCH(B7,'Asset Inventory'!$A$2:$A$21,0)),"Unknown asset") -> Third-party IT and EMR Vendor | D7: EMR vendor breach or outage affects patient data and availability | E7: No security clauses or SLA audit rights in contract | F7: 3 | G7: 5 | H7: =F7*G7 -> 15 | I7: =IF(H7>='Scoring Key'!$B$12,"Critical",IF(H7>='Scoring Key'!$B$11,"High",IF(H7>='Scoring Key'!$B$10,"Medium","Low"))) -> High | J7: Signed contract with SLA for uptime only | K7: A.5.19 Supplier relationships; A.5.20 Supplier agreements; A.5.23 Cloud services | L7: Mitigate | M7: Add security and breach-notification clauses; annual vendor assessment | N7: Procurement Manager | O7: 2027-06-30 | P7: 2 | Q7: 4 | R7: =P7*Q7 -> 8 | S7: =IF(R7>='Scoring Key'!$B$12,"Critical",IF(R7>='Scoring Key'!$B$11,"High",IF(R7>='Scoring Key'!$B$10,"Medium","Low"))) -> Medium | T7: Planned
A8: R-07 | B8: A-10 | C8: =IFERROR(INDEX('Asset Inventory'!$B$2:$B$21,MATCH(B8,'Asset Inventory'!$A$2:$A$21,0)),"Unknown asset") -> Doctor Laptops (~35) | D8: Loss or theft of doctor laptops with patient data | E8: Laptops not encrypted | F8: 3 | G8: 4 | H8: =F8*G8 -> 12 | I8: =IF(H8>='Scoring Key'!$B$12,"Critical",IF(H8>='Scoring Key'!$B$11,"High",IF(H8>='Scoring Key'!$B$10,"Medium","Low"))) -> High | J8: Asset tagging | K8: A.8.1 User endpoint devices; A.8.24 Use of cryptography | L8: Mitigate | M8: Enable full-disk encryption (BitLocker) and remote wipe | N8: IT Support Lead | O8: 2027-01-15 | P8: 1 | Q8: 3 | R8: =P8*Q8 -> 3 | S8: =IF(R8>='Scoring Key'!$B$12,"Critical",IF(R8>='Scoring Key'!$B$11,"High",IF(R8>='Scoring Key'!$B$10,"Medium","Low"))) -> Low | T8: In progress
A9: R-08 | B9: A-04 | C9: =IFERROR(INDEX('Asset Inventory'!$B$2:$B$21,MATCH(B9,'Asset Inventory'!$A$2:$A$21,0)),"Unknown asset") -> Core DB Server | D9: Server room outage (power, cooling, fire) | E9: Single UPS; no environmental monitoring | F9: 2 | G9: 5 | H9: =F9*G9 -> 10 | I9: =IF(H9>='Scoring Key'!$B$12,"Critical",IF(H9>='Scoring Key'!$B$11,"High",IF(H9>='Scoring Key'!$B$10,"Medium","Low"))) -> High | J9: UPS; fire extinguisher | K9: A.7.5 Protecting against physical threats; A.8.14 Redundancy | L9: Mitigate | M9: Environmental sensors; second UPS; DR plan | N9: Facilities Manager | O9: 2027-05-31 | P9: 2 | Q9: 3 | R9: =P9*Q9 -> 6 | S9: =IF(R9>='Scoring Key'!$B$12,"Critical",IF(R9>='Scoring Key'!$B$11,"High",IF(R9>='Scoring Key'!$B$10,"Medium","Low"))) -> Medium | T9: Planned
A10: R-09 | B10: A-12 | C10: =IFERROR(INDEX('Asset Inventory'!$B$2:$B$21,MATCH(B10,'Asset Inventory'!$A$2:$A$21,0)),"Unknown asset") -> Active Directory | D10: Privileged account compromise in Active Directory | E10: No PAM; admin accounts used for daily work | F10: 3 | G10: 5 | H10: =F10*G10 -> 15 | I10: =IF(H10>='Scoring Key'!$B$12,"Critical",IF(H10>='Scoring Key'!$B$11,"High",IF(H10>='Scoring Key'!$B$10,"Medium","Low"))) -> High | J10: Password policy | K10: A.8.2 Privileged access rights; A.8.5 Secure authentication | L10: Mitigate | M10: Separate admin accounts; MFA; tiered admin model | N10: IT Manager | O10: 2027-03-15 | P10: 2 | Q10: 4 | R10: =P10*Q10 -> 8 | S10: =IF(R10>='Scoring Key'!$B$12,"Critical",IF(R10>='Scoring Key'!$B$11,"High",IF(R10>='Scoring Key'!$B$10,"Medium","Low"))) -> Medium | T10: Planned
A11: R-10 | B11: A-08 | C11: =IFERROR(INDEX('Asset Inventory'!$B$2:$B$21,MATCH(B11,'Asset Inventory'!$A$2:$A$21,0)),"Unknown asset") -> Branch VPN Links | D11: Interception or misuse of branch VPN traffic | E11: Old VPN configuration; weak pre-shared keys | F11: 2 | G11: 4 | H11: =F11*G11 -> 8 | I11: =IF(H11>='Scoring Key'!$B$12,"Critical",IF(H11>='Scoring Key'!$B$11,"High",IF(H11>='Scoring Key'!$B$10,"Medium","Low"))) -> Medium | J11: IPsec VPN | K11: A.8.20 Networks security; A.8.24 Use of cryptography | L11: Mitigate | M11: Rotate keys; move to certificate-based VPN; review configs | N11: Network Administrator | O11: 2027-02-28 | P11: 1 | Q11: 3 | R11: =P11*Q11 -> 3 | S11: =IF(R11>='Scoring Key'!$B$12,"Critical",IF(R11>='Scoring Key'!$B$11,"High",IF(R11>='Scoring Key'!$B$10,"Medium","Low"))) -> Low | T11: Planned
A12: R-11 | B12: A-15 | C12: =IFERROR(INDEX('Asset Inventory'!$B$2:$B$21,MATCH(B12,'Asset Inventory'!$A$2:$A$21,0)),"Unknown asset") -> Payment POS and Billing System | D12: Payment card data theft from POS | E12: POS terminals on same VLAN as workstations | F12: 2 | G12: 4 | H12: =F12*G12 -> 8 | I12: =IF(H12>='Scoring Key'!$B$12,"Critical",IF(H12>='Scoring Key'!$B$11,"High",IF(H12>='Scoring Key'!$B$10,"Medium","Low"))) -> Medium | J12: Provider-managed terminals | K12: A.8.22 Segregation of networks; A.5.34 Privacy and protection of PII | L12: Mitigate | M12: Dedicated POS VLAN; follow PCI DSS guidance | N12: Finance Manager | O12: 2027-03-31 | P12: 1 | Q12: 3 | R12: =P12*Q12 -> 3 | S12: =IF(R12>='Scoring Key'!$B$12,"Critical",IF(R12>='Scoring Key'!$B$11,"High",IF(R12>='Scoring Key'!$B$10,"Medium","Low"))) -> Low | T12: Planned
A13: R-12 | B13: A-11 | C13: =IFERROR(INDEX('Asset Inventory'!$B$2:$B$21,MATCH(B13,'Asset Inventory'!$A$2:$A$21,0)),"Unknown asset") -> Email and Collaboration (SaaS) | D13: Sensitive data leaked via email or personal cloud sharing | E13: No DLP; no data classification | F13: 4 | G13: 3 | H13: =F13*G13 -> 12 | I13: =IF(H13>='Scoring Key'!$B$12,"Critical",IF(H13>='Scoring Key'!$B$11,"High",IF(H13>='Scoring Key'!$B$10,"Medium","Low"))) -> High | J13: Acceptable use policy | K13: A.5.12 Classification of information; A.8.12 Data leakage prevention | L13: Mitigate | M13: Data classification scheme; DLP rules for patient IDs | N13: IT Manager | O13: 2027-04-30 | P13: 2 | Q13: 2 | R13: =P13*Q13 -> 4 | S13: =IF(R13>='Scoring Key'!$B$12,"Critical",IF(R13>='Scoring Key'!$B$11,"High",IF(R13>='Scoring Key'!$B$10,"Medium","Low"))) -> Low | T13: Planned
... A17: R-16 | B17: A-19 | C17: =IFERROR(INDEX('Asset Inventory'!$B$2:$B$21,MATCH(B17,'Asset Inventory'!$A$2:$A$21,0)),"Unknown asset") -> IT Team (5 staff) | D17: Key IT admin leaves, causing knowledge loss and access gaps | E17: No documentation; no offboarding checklist | F17: 3 | G17: 4 | H17: =F17*G17 -> 12 | I17: =IF(H17>='Scoring Key'!$B$12,"Critical",IF(H17>='Scoring Key'!$B$11,"High",IF(H17>='Scoring Key'!$B$10,"Medium","Low"))) -> High | J17: None | K17: A.6.5 Responsibilities after termination; A.5.37 Documented operating procedures | L17: Mitigate | M17: Runbooks; offboarding checklist; access revocation SLA | N17: IT Manager | O17: 2027-01-31 | P17: 2 | Q17: 2 | R17: =P17*Q17 -> 4 | S17: =IF(R17>='Scoring Key'!$B$12,"Critical",IF(R17>='Scoring Key'!$B$11,"High",IF(R17>='Scoring Key'!$B$10,"Medium","Low"))) -> Low | T17: Planned

Sheet Scoring Key
A1: Level | B1: Likelihood (1-5) | C1: Impact (1-5)
A2: 1 | B2: Rare – unlikely in 3+ years | C2: Negligible – no real effect on patients or operations
A3: 2 | B3: Unlikely – once every 1-3 years | C3: Minor – small disruption, no data exposed
A4: 3 | B4: Possible – once a year | C4: Moderate – clinic disruption for a day, limited data exposure
A5: 4 | B5: Likely – several times a year | C5: Major – multi-day outage or exposure of patient records
A6: 5 | B6: Almost certain – monthly or more | C6: Severe – patient safety risk, mass data breach, legal action
A8: Risk level thresholds (score = L x I) | B8: Min score | C8: Level
B9: 1 | C9: Low
B10: 5 | C10: Medium
B11: 10 | C11: High
B12: 17 | C12: Critical
A14: Asset C/I/A rating | B14: Meaning
A15: 1 | B15: Low – little harm if compromised
A16: 2 | B16: Medium – noticeable harm
A17: 3 | B17: High – serious harm (patient safety, legal, financial)
A19: Asset criticality (formula) | B19: Highest of C, I, A: 1 = Low, 2 = Medium, 3 = High

Sheet Summary
A1: Risk Level | B1: Inherent (before treatment) | C1: Residual (after planned treatment)
A2: Critical | B2: =COUNTIF('Risk Register'!$I$2:$I$17,A2) -> 2 | C2: =COUNTIF('Risk Register'!$S$2:$S$17,A2) -> 0
A3: High | B3: =COUNTIF('Risk Register'!$I$2:$I$17,A3) -> 10 | C3: =COUNTIF('Risk Register'!$S$2:$S$17,A3) -> 0
A4: Medium | B4: =COUNTIF('Risk Register'!$I$2:$I$17,A4) -> 4 | C4: =COUNTIF('Risk Register'!$S$2:$S$17,A4) -> 9
A5: Low | B5: =COUNTIF('Risk Register'!$I$2:$I$17,A5) -> 0 | C5: =COUNTIF('Risk Register'!$S$2:$S$17,A5) -> 7
A6: Total | B6: =SUM(B2:B5) -> 16 | C6: =SUM(C2:C5) -> 16
A8: Average score | B8: =AVERAGE('Risk Register'!$H$2:$H$17) -> 13.0625 | C8: =AVERAGE('Risk Register'!$R$2:$R$17) -> 5.5
A9: Risk reduction | C9: =IF(B8=0,0,1-C8/B8) -> 0.57894737
